odoo/addons/account_move_line_accounting_description_purchase/README.rst
odoo/addons/account_move_line_accounting_description_purchase/__init__.py
odoo/addons/account_move_line_accounting_description_purchase/__manifest__.py
odoo/addons/account_move_line_accounting_description_purchase/i18n/account_move_line_accounting_description_purchase.pot
odoo/addons/account_move_line_accounting_description_purchase/i18n/es.po
odoo/addons/account_move_line_accounting_description_purchase/i18n/it.po
odoo/addons/account_move_line_accounting_description_purchase/models/__init__.py
odoo/addons/account_move_line_accounting_description_purchase/models/purchase_order.py
odoo/addons/account_move_line_accounting_description_purchase/readme/CONTRIBUTORS.rst
odoo/addons/account_move_line_accounting_description_purchase/readme/DESCRIPTION.rst
odoo/addons/account_move_line_accounting_description_purchase/static/description/icon.png
odoo/addons/account_move_line_accounting_description_purchase/static/description/index.html
odoo/addons/account_move_line_accounting_description_purchase/tests/__init__.py
odoo/addons/account_move_line_accounting_description_purchase/tests/test_purchase_order_description.py
odoo14_addon_account_move_line_accounting_description_purchase-14.0.1.0.1.dev10.dist-info/METADATA
odoo14_addon_account_move_line_accounting_description_purchase-14.0.1.0.1.dev10.dist-info/WHEEL
odoo14_addon_account_move_line_accounting_description_purchase-14.0.1.0.1.dev10.dist-info/top_level.txt
odoo14_addon_account_move_line_accounting_description_purchase-14.0.1.0.1.dev10.dist-info/RECORD
